moderatorpy/__init__.py
moderatorpy/http_limiter.py
moderatorpy/redis_bucket.py
moderatorpy/async_/__init__.py
moderatorpy/async_/http_limiter.py
moderatorpy/async_/redis_bucket.py
moderatorpy-0.1.1.dist-info/METADATA
moderatorpy-0.1.1.dist-info/WHEEL
moderatorpy-0.1.1.dist-info/RECORD
