Metadata-Version: 2.3
Name: moderatorpy
Version: 0.1.1
Summary: Add your description here
Author-email: Kevin Hill <kivo360@gmail.com>
Requires-Python: >=3.10
Requires-Dist: httpx>=0.27.2
Requires-Dist: pyrate-limiter
Requires-Dist: redis[hiredis]>=5.0.0
